LICENSE
MANIFEST.in
README.md
README.rst
setup.cfg
setup.py
examples/cookbook-plain/cookbook/ingredients/fixtures/ingredients.json
examples/cookbook/cookbook/ingredients/fixtures/ingredients.json
graphene_django/__init__.py
graphene_django/compat.py
graphene_django/conftest.py
graphene_django/constants.py
graphene_django/converter.py
graphene_django/fields.py
graphene_django/registry.py
graphene_django/settings.py
graphene_django/types.py
graphene_django/views.py
graphene_django/debug/__init__.py
graphene_django/debug/middleware.py
graphene_django/debug/types.py
graphene_django/debug/sql/__init__.py
graphene_django/debug/sql/tracking.py
graphene_django/debug/sql/types.py
graphene_django/debug/tests/__init__.py
graphene_django/debug/tests/test_query.py
graphene_django/filter/__init__.py
graphene_django/filter/fields.py
graphene_django/filter/filterset.py
graphene_django/filter/utils.py
graphene_django/filter/tests/__init__.py
graphene_django/filter/tests/filters.py
graphene_django/filter/tests/test_fields.py
graphene_django/filter/tests/test_in_filter.py
graphene_django/forms/__init__.py
graphene_django/forms/converter.py
graphene_django/forms/forms.py
graphene_django/forms/mutation.py
graphene_django/forms/types.py
graphene_django/forms/tests/__init__.py
graphene_django/forms/tests/test_converter.py
graphene_django/forms/tests/test_mutation.py
graphene_django/management/__init__.py
graphene_django/management/commands/__init__.py
graphene_django/management/commands/graphql_schema.py
graphene_django/rest_framework/__init__.py
graphene_django/rest_framework/models.py
graphene_django/rest_framework/mutation.py
graphene_django/rest_framework/serializer_converter.py
graphene_django/rest_framework/types.py
graphene_django/rest_framework/tests/__init__.py
graphene_django/rest_framework/tests/test_field_converter.py
graphene_django/rest_framework/tests/test_multiple_model_serializers.py
graphene_django/rest_framework/tests/test_mutation.py
graphene_django_patch.egg-info/PKG-INFO
graphene_django_patch.egg-info/SOURCES.txt
graphene_django_patch.egg-info/dependency_links.txt
graphene_django_patch.egg-info/not-zip-safe
graphene_django_patch.egg-info/requires.txt
graphene_django_patch.egg-info/top_level.txt