Metadata-Version: 2.1
Name: graphene-django-patch
Version: 2.15.0.0
Summary: Graphene Django integration
Home-page: https://github.com/gabrielsebag/graphene-django
Author: Gabriel Sebag
Author-email: hello@gabrielsebag.com
License: MIT
Keywords: api graphql protocol rest relay graphene
Platform: any
Classifier: Development Status :: 3 - Alpha
Classifier: Intended Audience :: Developers
Classifier: Topic :: Software Development :: Libraries
Classifier: Programming Language :: Python :: 2
Classifier: Programming Language :: Python :: 2.7
Classifier: Programming Language :: Python :: 3
Classifier: Programming Language :: Python :: 3.6
Classifier: Programming Language :: Python :: 3.7
Classifier: Programming Language :: Python :: 3.8
Classifier: Programming Language :: Python :: Implementation :: PyPy
Classifier: Framework :: Django
Classifier: Framework :: Django :: 1.11
Classifier: Framework :: Django :: 2.2
Classifier: Framework :: Django :: 3.0
Provides-Extra: test
Provides-Extra: rest_framework
Provides-Extra: dev
License-File: LICENSE
